[
  { "authors": "Sun Q, Liu T, Yu X, et al.", "title": "Non-interference NDIR detection method for mixed gases based on differential elimination", "journal": "Sensors and Actuators B: Chemical", "year": 2023, "vol": "390", "pages": "133901", "badge": "中科院一区TOP · IF=8.4", "tag": "一作" },
  { "authors": "Sun Q, Liu T, Huang M, et al.", "title": "High Accuracy Wide Range CO2 Detection Method Based on Difference Optical Path NDIR", "journal": "Sensors and Actuators A: Physical", "year": 2023, "vol": "363", "pages": "114722", "badge": "中科院二区 · IF=4.6", "tag": "一作" },
  { "authors": "Sun Q, Liu T, Huang M, et al.", "title": "Rapid Recognition and Concentration Prediction of Gas Mixtures Based on SMLP", "journal": "IEEE Trans. Instrumentation & Measurement", "year": 2024, "vol": "73", "pages": "1-9", "badge": "中科院二区TOP · IF=5.6", "tag": "一作" },
  { "authors": "Kong L, Yu X, Sun Q, et al.", "title": "Rapid and accurate detection of food additives in liquid environments via SERS", "journal": "Food Bioscience", "year": 2025, "pages": "106804", "badge": "中科院一区TOP · IF=5.9", "tag": "合作" },
  { "authors": "Yu X, Liu T*, Kong L, Lan T, Sun Q, et al.", "title": "SpecRecFormer: Deep Learning-Driven Adaptive Component Identification of PAH Mixtures", "journal": "Analytical Chemistry", "year": 2025, "vol": "97(18)", "pages": "9876-9883", "badge": "中科院一区TOP · IF=6.7", "tag": "合作" },
  { "authors": "Yu X, Kong L, Lan T, Chen J, Sun Q, et al.", "title": "Enrichment-enhancement membrane SERS substrate for PAH detection", "journal": "Spectrochimica Acta A", "year": 2025, "vol": "328", "pages": "125429", "badge": "中科院二区 · IF=4.6", "tag": "合作" },
  { "authors": "Yu X, Lan T, Kong L, Liu T, Sun Q, et al.", "title": "Ultra-stable Ag-HP-β-CD/GO/NCF SERS substrate with coffee-ring effect for PAHs", "journal": "Surfaces and Interfaces", "year": 2024, "vol": "44", "pages": "103763", "badge": "中科院二区 · IF=5.7", "tag": "合作" },
  { "authors": "Qu F, Li H, Sun Q, et al.", "title": "High-accuracy quantification of soil elements by LIBS based on PCA-GS-ELM", "journal": "J. Analytical Atomic Spectrometry", "year": 2024, "vol": "39(10)", "pages": "2514-2521", "badge": "中科院一区 · IF=3.1", "tag": "合作" },
  { "authors": "Kong L, Yu X, Sun Q, et al.", "title": "Sensitive and Stable NCF/GO/Au@Ag SERS Substrate for PAHs", "journal": "Polymers", "year": 2025, "vol": "17(12)", "pages": "1716", "badge": "中科院三区 · IF=4.9", "tag": "合作" },
  { "authors": "Xu J, Wang J, Rao J, Sun Q, et al.", "title": "Parallel cross entropy policy gradient ADP for optimal tracking control", "journal": "IEEE Trans. Systems Man Cybernetics: Systems", "year": 2024, "vol": "54(6)", "pages": "3809-3821", "badge": "中科院一区 · IF=8.7", "tag": "合作" }
]